{
  "openapi": "3.0.1",
  "info": {
    "title": "CineReserve.API",
    "version": "1.0"
  },
  "paths": {
    "/api/Auth/login": {
      "post": {
        "tags": [
          "Auth"
        ],
        "requestBody": {
          "content": {
            "application/json": {
              "schema": {
                "$ref": "#/components/schemas/LoginRequest"
              }
            },
            "text/json": {
              "schema": {
                "$ref": "#/components/schemas/LoginRequest"
              }
            },
            "application/*+json": {
              "schema": {
                "$ref": "#/components/schemas/LoginRequest"
              }
            }
          }
        },
        "responses": {
          "200": {
            "description": "OK"
          }
        }
      }
    },
    "/api/Bookings": {
      "post": {
        "tags": [
          "Bookings"
        ],
        "requestBody": {
          "content": {
            "application/json": {
              "schema": {
                "$ref": "#/components/schemas/BookingRequestDto"
              }
            },
            "text/json": {
              "schema": {
                "$ref": "#/components/schemas/BookingRequestDto"
              }
            },
            "application/*+json": {
              "schema": {
                "$ref": "#/components/schemas/BookingRequestDto"
              }
            }
          }
        },
        "responses": {
          "200": {
            "description": "OK"
          }
        }
      }
    },
    "/api/Movies": {
      "get": {
        "tags": [
          "Movies"
        ],
        "responses": {
          "200": {
            "description": "OK"
          }
        }
      },
      "post": {
        "tags": [
          "Movies"
        ],
        "requestBody": {
          "content": {
            "application/json": {
              "schema": {
                "$ref": "#/components/schemas/Movie"
              }
            },
            "text/json": {
              "schema": {
                "$ref": "#/components/schemas/Movie"
              }
            },
            "application/*+json": {
              "schema": {
                "$ref": "#/components/schemas/Movie"
              }
            }
          }
        },
        "responses": {
          "200": {
            "description": "OK"
          }
        }
      }
    },
    "/api/Showtimes": {
      "get": {
        "tags": [
          "Showtimes"
        ],
        "responses": {
          "200": {
            "description": "OK"
          }
        }
      },
      "post": {
        "tags": [
          "Showtimes"
        ],
        "requestBody": {
          "content": {
            "application/json": {
              "schema": {
                "$ref": "#/components/schemas/Showtime"
              }
            },
            "text/json": {
              "schema": {
                "$ref": "#/components/schemas/Showtime"
              }
            },
            "application/*+json": {
              "schema": {
                "$ref": "#/components/schemas/Showtime"
              }
            }
          }
        },
        "responses": {
          "200": {
            "description": "OK"
          }
        }
      }
    },
    "/api/Showtimes/{id}/seats": {
      "get": {
        "tags": [
          "Showtimes"
        ],
        "parameters": [
          {
            "name": "id",
            "in": "path",
            "required": true,
            "schema": {
              "type": "integer",
              "format": "int32"
            }
          }
        ],
        "responses": {
          "200": {
            "description": "OK"
          }
        }
      }
    }
  },
  "components": {
    "schemas": {
      "BookingRequestDto": {
        "type": "object",
        "properties": {
          "showtimeId": {
            "type": "integer",
            "format": "int32"
          },
          "seats": {
            "type": "array",
            "items": {
              "$ref": "#/components/schemas/SeatDto"
            },
            "nullable": true
          }
        },
        "additionalProperties": false
      },
      "LoginRequest": {
        "type": "object",
        "properties": {
          "username": {
            "type": "string",
            "nullable": true
          },
          "password": {
            "type": "string",
            "nullable": true
          }
        },
        "additionalProperties": false
      },
      "Movie": {
        "type": "object",
        "properties": {
          "id": {
            "type": "integer",
            "format": "int32"
          },
          "title": {
            "type": "string",
            "nullable": true
          },
          "duration": {
            "type": "integer",
            "format": "int32"
          },
          "genre": {
            "type": "string",
            "nullable": true
          }
        },
        "additionalProperties": false
      },
      "SeatDto": {
        "type": "object",
        "properties": {
          "rowNumber": {
            "type": "string",
            "nullable": true
          },
          "seatNumber": {
            "type": "integer",
            "format": "int32"
          }
        },
        "additionalProperties": false
      },
      "Showtime": {
        "type": "object",
        "properties": {
          "id": {
            "type": "integer",
            "format": "int32"
          },
          "movieId": {
            "type": "integer",
            "format": "int32"
          },
          "showDate": {
            "type": "string",
            "format": "date-time"
          },
          "showTime": {
            "type": "string",
            "format": "date-span"
          },
          "hallName": {
            "type": "string",
            "nullable": true
          },
          "movie": {
            "$ref": "#/components/schemas/Movie"
          }
        },
        "additionalProperties": false
      }
    }
  }
}